freecall/__init__.py
freecall/freecall.py
freecall-1.0.4.dist-info/WHEEL
freecall-1.0.4.dist-info/METADATA
freecall-1.0.4.dist-info/RECORD
