Metadata-Version: 2.1
Name: freecall
Version: 1.0.4
Summary: 
Author: Zenith
Author-email: z@zenith.dev
Requires-Python: >=3.6,<4.0
Classifier: Programming Language :: Python :: 3
Classifier: Programming Language :: Python :: 3.6
Classifier: Programming Language :: Python :: 3.7
Classifier: Programming Language :: Python :: 3.8
Requires-Dist: dill (>=0.3.2,<0.4.0)
